CHANGES.rst
CONTRIBUTORS.rst
DEVELOP.rst
LICENSE.GPL
LICENSE.rst
MANIFEST.in
README.rst
setup.cfg
setup.py
src/collective/__init__.py
src/collective.denyroles.egg-info/PKG-INFO
src/collective.denyroles.egg-info/SOURCES.txt
src/collective.denyroles.egg-info/dependency_links.txt
src/collective.denyroles.egg-info/entry_points.txt
src/collective.denyroles.egg-info/namespace_packages.txt
src/collective.denyroles.egg-info/not-zip-safe
src/collective.denyroles.egg-info/requires.txt
src/collective.denyroles.egg-info/top_level.txt
src/collective/denyroles/__init__.py
src/collective/denyroles/config.py
src/collective/denyroles/configure.zcml
src/collective/denyroles/patches.py
src/collective/denyroles/testing.py
src/collective/denyroles/utils.py
src/collective/denyroles/tests/__init__.py
src/collective/denyroles/tests/test_functional.py
src/collective/denyroles/tests/test_utils.py