Metadata-Version: 2.1
Name: collective.denyroles
Version: 1.0.0b2
Summary: Plone PAS patch for denying access to editors and managers
Home-page: https://github.com/collective/collective.denyroles/
Author: Maurits van Rees
Author-email: m.van.rees@zestsoftware.nl
License: GPL version 2
Keywords: Python Plone
Platform: UNKNOWN
Classifier: Development Status :: 4 - Beta
Classifier: Environment :: Web Environment
Classifier: Framework :: Plone
Classifier: Framework :: Plone :: 4.3
Classifier: Framework :: Plone :: 5.1
Classifier: Programming Language :: Python
Classifier: Programming Language :: Python :: 2.7
Classifier: Operating System :: OS Independent
Classifier: License :: OSI Approved :: GNU General Public License v2 (GPLv2)
Provides-Extra: test
